<?xml version="1.0" encoding="UTF-8" standalone="no"?><Jugadores>


    <Jugador codigoequipo="A" dni="44686144L">
        <nombre>Gorka</nombre>
        <apellido>Armas</apellido>
        <telefono>660058538</telefono>
        <fechanacimiento>04/02/1980</fechanacimiento>
        <demarcacion>Delantero</demarcacion>
        <salario>1200</salario>
    </Jugador>
<Jugador codigoequipo="A" dni="44686144F"><nombre>Andoni</nombre><apellido>Pérez</apellido><telefono>660058538</telefono><fechanacimiento>04/02/1980</fechanacimiento><demarcacion>Delantero</demarcacion><salario>1100</salario></Jugador><Jugador codigoequipo="A" dni="45678925L"><nombre>Pedro</nombre><apellido>I</apellido><telefono>69325874</telefono><fechanacimiento>01/01/1991</fechanacimiento><demarcacion>Delantero</demarcacion><salario>900</salario></Jugador></Jugadores>